ucast/__init__.py
ucast/__main__.py
ucast/bokeh.py
ucast/io.py
ucast/plot.py
ucast/request.py
ucast/site.py
ucast/utils.py
ucast/radtran/__init__.py
ucast/radtran/am/__init__.py
ucast/radtran/am/config.py
ucast/radtran/am/core.py
ucast/weather/__init__.py
ucast/weather/gfs/__init__.py
ucast/weather/gfs/core.py
ucast/weather/gfs/cycle.py
ucast/weather/gfs/grib.py
ucast/weather/gfs/nomads.py
ucast-0.1.3.dist-info/LICENSE
ucast-0.1.3.dist-info/METADATA
ucast-0.1.3.dist-info/WHEEL
ucast-0.1.3.dist-info/entry_points.txt
ucast-0.1.3.dist-info/top_level.txt
ucast-0.1.3.dist-info/RECORD
