Metadata-Version: 2.1
Name: ucast
Version: 0.1.3
Summary: Micro-weather forecasting for astronomy
Home-page: https://github.com/focisrc/ucast
Author: Chi-kwan Chan
Author-email: chanc@arizona.edu
License: UNKNOWN
Platform: UNKNOWN
Requires-Python: >=3.6
Requires-Dist: click (>=7.1.2)
Requires-Dist: matplotlib (>=3.2.2)
Requires-Dist: numpy (>=1.18.5)
Requires-Dist: pandas (>=1.0.5)
Requires-Dist: pygrib (>=2.0.4)
Requires-Dist: requests (>=2.24.0)
Requires-Dist: tqdm (>=4.46.1)
Requires-Dist: bokeh (>=2.3.0)
